runlocal_hub/__init__.py
runlocal_hub/client.py
runlocal_hub/devices/__init__.py
runlocal_hub/devices/filters.py
runlocal_hub/devices/selector.py
runlocal_hub/exceptions.py
runlocal_hub/http/__init__.py
runlocal_hub/http/client.py
runlocal_hub/jobs/__init__.py
runlocal_hub/jobs/poller.py
runlocal_hub/models/__init__.py
runlocal_hub/models/benchmark.py
runlocal_hub/models/benchmark_result.py
runlocal_hub/models/device.py
runlocal_hub/models/job.py
runlocal_hub/models/model.py
runlocal_hub/models/prediction.py
runlocal_hub/models/responses.py
runlocal_hub/models/settings/__init__.py
runlocal_hub/models/settings/common.py
runlocal_hub/models/settings/coreml.py
runlocal_hub/models/settings/onnx.py
runlocal_hub/models/settings/openvino.py
runlocal_hub/models/settings/tflite.py
runlocal_hub/models/tensor.py
runlocal_hub/py.typed
runlocal_hub/tensors/__init__.py
runlocal_hub/tensors/handler.py
runlocal_hub/utils/__init__.py
runlocal_hub/utils/console.py
runlocal_hub/utils/decorators.py
runlocal_hub/utils/display.py
runlocal_hub-0.1.7.dist-info/licenses/LICENSE.txt
runlocal_hub-0.1.7.dist-info/WHEEL
runlocal_hub-0.1.7.dist-info/METADATA
runlocal_hub-0.1.7.dist-info/RECORD
