Metadata-Version: 2.4
Name: runlocal-hub
Version: 0.1.7
Summary: Python client for benchmarking and validating ML models on real devices via RunLocal API
Keywords: machine-learning,models,benchmarking,coreml,onnx,tflite,openvino,ml-ops,device-testing,model-optimization,inference,neural-networks
Author: RunLocal
Author-email: RunLocal <ciaran@runlocal.ai>
License-Expression: MIT
License-File: LICENSE.txt
Classifier: Development Status :: 4 - Beta
Classifier: Intended Audience :: Developers
Classifier: Intended Audience :: Science/Research
Classifier: Topic :: Software Development :: Libraries :: Python Modules
Classifier: Topic :: Scientific/Engineering :: Artificial Intelligence
Classifier: Operating System :: OS Independent
Classifier: Programming Language :: Python :: 3.10
Classifier: Programming Language :: Python :: 3.11
Classifier: Programming Language :: Python :: 3.12
Classifier: Programming Language :: Python :: 3.13
Requires-Dist: numpy>=1.19.0
Requires-Dist: pydantic>=2.0.0,<3.0.0
Requires-Dist: requests>=2.25.0,<3.0.0
Requires-Dist: tqdm>=4.50.0
Requires-Dist: rich>=10.0.0
Maintainer: Ciaran O'Rourke
Maintainer-email: Ciaran O'Rourke <ciaran@runlocal.ai>
Requires-Python: >=3.10
Project-URL: Changelog, https://github.com/neuralize-ai/runlocal_hub/blob/main/CHANGELOG.md
Project-URL: Homepage, https://runlocal.ai
Project-URL: Issues, https://github.com/neuralize-ai/runlocal_hub/issues
Project-URL: Repository, https://github.com/neuralize-ai/runlocal_hub
